<?xml version="1.0" encoding="utf-8" ?>
<dwsync>
<file name="login&register.php" server="gallina.comeze.com/public_html/" local="130651576810000000" remote="130651529400000000" Dst="2" />
<file name="form_login.php" server="gallina.comeze.com/public_html/" local="130651558674879114" remote="130651496400000000" Dst="2" />
<file name="getCurlData.php" server="gallina.comeze.com/public_html/" local="130637507824525509" remote="130637437200000000" Dst="2" />
<file name="ad_bottom.php" server="gallina.comeze.com/public_html/" local="130629757634859662" remote="130629715800000000" Dst="2" />
<file name="ad_vertical.php" server="gallina.comeze.com/public_html/" local="130629757642864962" remote="130629715800000000" Dst="2" />
<file name="login&register.php" server="ftp.byethost16.com//htdocs/" local="130663284595795359" remote="130663214400000000" Dst="2" />
<file name="form_login.php" server="ftp.byethost16.com//htdocs/" local="130667027343815090" remote="130666957200000000" Dst="2" />
<file name="header.php" server="ftp.byethost16.com//htdocs/" local="130656357012182983" remote="130656287400000000" Dst="2" />
<file name="user.php" server="ftp.byethost16.com//htdocs/" local="130656388018787256" remote="130656320400000000" Dst="2" />
<file name="plus.php" server="ftp.byethost16.com//htdocs/" local="130656470847677824" remote="130656400800000000" Dst="2" />
</dwsync>